ANCIENT_INVASION/ancient_invasion.py
ANCIENT_INVASION/ancient_invasion_tests.py
ANCIENT_INVASION-1.dist-info/LICENSE
ANCIENT_INVASION-1.dist-info/METADATA
ANCIENT_INVASION-1.dist-info/WHEEL
ANCIENT_INVASION-1.dist-info/entry_points.txt
ANCIENT_INVASION-1.dist-info/top_level.txt
ANCIENT_INVASION-1.dist-info/RECORD
