Metadata-Version: 2.1
Name: ANCIENT-INVASION
Version: 1
Summary: This package contains implementation of the offline turn-based strategy RPG "ANCIENT_INVASION" on command line interface.
Home-page: https://github.com/NativeApkDev/ANCIENT_INVASION
Author: NativeApkDev
Author-email: nativeapkdev2021@gmail.com
License: MIT
Platform: UNKNOWN
Classifier: Programming Language :: Python :: 3
Classifier: Programming Language :: Python :: 3.7
